xlerai/__init__.py
xlerai/__main__.py
xlerai/xlerai/__init__.py
xlerai-1.12.0.dist-info/LICENSE
xlerai-1.12.0.dist-info/METADATA
xlerai-1.12.0.dist-info/WHEEL
xlerai-1.12.0.dist-info/RECORD
