Metadata-Version: 2.1
Name: xlerai
Version: 1.12.0
Summary: The official Python library for the xler.ai API
License: Apache-2.0
Author: XlerAI
Requires-Python: >=3.7.1
Classifier: License :: OSI Approved :: Apache Software License
Classifier: Programming Language :: Python :: 3
Classifier: Programming Language :: Python :: 3.8
Classifier: Programming Language :: Python :: 3.9
Classifier: Programming Language :: Python :: 3.10
Classifier: Programming Language :: Python :: 3.11
Classifier: Programming Language :: Python :: 3.12
Requires-Dist: openai (==1.12.0)
